{
  "version": "1.1.10",
  "commands": {
    "cm:stacks:validate-regex": {
      "id": "cm:stacks:validate-regex",
      "description": "This command is used to find all the invalid regexes present in the content types and global fields of your stack.",
      "strict": true,
      "pluginName": "@contentstack/cli-cm-regex-validate",
      "pluginAlias": "@contentstack/cli-cm-regex-validate",
      "pluginType": "core",
      "aliases": [],
      "examples": [
        "$ csdx cm:stacks:validate-regex",
        "$ csdx cm:stacks:validate-regex -a <management_token_alias>",
        "$ csdx cm:stacks:validate-regex -c",
        "$ csdx cm:stacks:validate-regex -g",
        "$ csdx cm:stacks:validate-regex -f <path/to/the/directory>",
        "$ csdx cm:stacks:validate-regex -a <management_token_alias> -c -g",
        "$ csdx cm:stacks:validate-regex -a <management_token_alias> -c -g -f <path/to/the/directory>"
      ],
      "flags": {
        "help": {
          "name": "help",
          "type": "boolean",
          "char": "h",
          "description": "To show the flags that can be used with this CLI command",
          "allowNo": false
        },
        "alias": {
          "name": "alias",
          "type": "option",
          "char": "a",
          "description": "Alias (name) assigned to the management token",
          "multiple": false
        },
        "contentType": {
          "name": "contentType",
          "type": "boolean",
          "char": "c",
          "description": "To find invalid regexes within the content types",
          "allowNo": false
        },
        "globalField": {
          "name": "globalField",
          "type": "boolean",
          "char": "g",
          "description": "To find invalid regexes within the global fields",
          "allowNo": false
        },
        "filePath": {
          "name": "filePath",
          "type": "option",
          "char": "f",
          "description": "[optional] The path or the location in your file system where the CSV output file should be stored.",
          "multiple": false
        }
      },
      "args": {}
    }
  }
}